kalabash_postfix_autoreply/__init__.py
kalabash_postfix_autoreply/apps.py
kalabash_postfix_autoreply/factories.py
kalabash_postfix_autoreply/forms.py
kalabash_postfix_autoreply/handlers.py
kalabash_postfix_autoreply/kbash_extension.py
kalabash_postfix_autoreply/known_problems.py
kalabash_postfix_autoreply/models.py
kalabash_postfix_autoreply/serializers.py
kalabash_postfix_autoreply/tests.py
kalabash_postfix_autoreply/urls_api.py
kalabash_postfix_autoreply/views.py
kalabash_postfix_autoreply/viewsets.py
kalabash_postfix_autoreply/locale/cs_CZ/LC_MESSAGES/django.mo
kalabash_postfix_autoreply/locale/cs_CZ/LC_MESSAGES/django.po
kalabash_postfix_autoreply/locale/de/LC_MESSAGES/django.mo
kalabash_postfix_autoreply/locale/de/LC_MESSAGES/django.po
kalabash_postfix_autoreply/locale/el_GR/LC_MESSAGES/django.mo
kalabash_postfix_autoreply/locale/el_GR/LC_MESSAGES/django.po
kalabash_postfix_autoreply/locale/en/LC_MESSAGES/django.mo
kalabash_postfix_autoreply/locale/en/LC_MESSAGES/django.po
kalabash_postfix_autoreply/locale/es/LC_MESSAGES/django.mo
kalabash_postfix_autoreply/locale/es/LC_MESSAGES/django.po
kalabash_postfix_autoreply/locale/fr/LC_MESSAGES/django.mo
kalabash_postfix_autoreply/locale/fr/LC_MESSAGES/django.po
kalabash_postfix_autoreply/locale/it/LC_MESSAGES/django.mo
kalabash_postfix_autoreply/locale/it/LC_MESSAGES/django.po
kalabash_postfix_autoreply/locale/ja_JP/LC_MESSAGES/django.mo
kalabash_postfix_autoreply/locale/ja_JP/LC_MESSAGES/django.po
kalabash_postfix_autoreply/locale/nl_NL/LC_MESSAGES/django.mo
kalabash_postfix_autoreply/locale/nl_NL/LC_MESSAGES/django.po
kalabash_postfix_autoreply/locale/pl_PL/LC_MESSAGES/django.mo
kalabash_postfix_autoreply/locale/pl_PL/LC_MESSAGES/django.po
kalabash_postfix_autoreply/locale/pt_BR/LC_MESSAGES/django.mo
kalabash_postfix_autoreply/locale/pt_BR/LC_MESSAGES/django.po
kalabash_postfix_autoreply/locale/pt_PT/LC_MESSAGES/django.mo
kalabash_postfix_autoreply/locale/pt_PT/LC_MESSAGES/django.po
kalabash_postfix_autoreply-1.7.1.dist-info/LICENSE
kalabash_postfix_autoreply-1.7.1.dist-info/METADATA
kalabash_postfix_autoreply-1.7.1.dist-info/WHEEL
kalabash_postfix_autoreply-1.7.1.dist-info/top_level.txt
kalabash_postfix_autoreply-1.7.1.dist-info/RECORD
